google_sheets_mcpserver/__init__.py
google_sheets_mcpserver/model.py
google_sheets_mcpserver/server.py
google_sheets_mcpserver-0.1.3.dist-info/LICENSE
google_sheets_mcpserver-0.1.3.dist-info/METADATA
google_sheets_mcpserver-0.1.3.dist-info/WHEEL
google_sheets_mcpserver-0.1.3.dist-info/entry_points.txt
google_sheets_mcpserver-0.1.3.dist-info/RECORD
